mydemo/__init__.py
poetry_trail-0.1.0.dist-info/METADATA
poetry_trail-0.1.0.dist-info/WHEEL
poetry_trail-0.1.0.dist-info/RECORD
