Metadata-Version: 2.1
Name: poetry-trail
Version: 0.1.0
Summary: Setting Up Poetry
Author: Kabir Manandhar
Requires-Python: >=3.11,<3.14
Classifier: Programming Language :: Python :: 3
Classifier: Programming Language :: Python :: 3.11
Classifier: Programming Language :: Python :: 3.12
Requires-Dist: matplotlib (>=3.10.5,<4.0.0)
Requires-Dist: numpy (>=2.3.2,<3.0.0)
Requires-Dist: pandas (>=2.3.2,<3.0.0)
Requires-Dist: scikit-learn (>=1.7.1,<2.0.0)
Requires-Dist: scipy (>=1.16.1,<2.0.0)
Requires-Dist: torch (>=2.8.0,<3.0.0)
